[
  {
    "number": 1,
    "question": "What is the definition of history concept 1?",
    "subject": "history",
    "date": "2026-04-20"
  },
  {
    "number": 2,
    "question": "Which of the following best describes history concept 2?",
    "subject": "history",
    "date": "2026-04-20"
  },
  {
    "number": 3,
    "question": "Explain the concept of history concept 3.",
    "subject": "history",
    "date": "2026-04-20"
  },
  {
    "number": 4,
    "question": "What are the main characteristics of history concept 4?",
    "subject": "history",
    "date": "2026-04-20"
  },
  {
    "number": 5,
    "question": "How does history concept 5 relate to real-world applications?",
    "subject": "history",
    "date": "2026-04-20"
  },
  {
    "number": 6,
    "question": "What is the significance of history concept 6?",
    "subject": "history",
    "date": "2026-04-20"
  },
  {
    "number": 7,
    "question": "Name three key points about history concept 7.",
    "subject": "history",
    "date": "2026-04-20"
  },
  {
    "number": 8,
    "question": "Describe the process of history concept 8.",
    "subject": "history",
    "date": "2026-04-20"
  },
  {
    "number": 9,
    "question": "What is an example of history concept 9?",
    "subject": "history",
    "date": "2026-04-20"
  },
  {
    "number": 10,
    "question": "How would you categorize history concept 10?",
    "subject": "history",
    "date": "2026-04-20"
  },
  {
    "number": 11,
    "question": "Define history concept 11 in your own words.",
    "subject": "history",
    "date": "2026-04-20"
  },
  {
    "number": 12,
    "question": "What does history concept 12 mean?",
    "subject": "history",
    "date": "2026-04-20"
  },
  {
    "number": 13,
    "question": "Briefly explain history concept 13.",
    "subject": "history",
    "date": "2026-04-20"
  },
  {
    "number": 14,
    "question": "State one important fact about history concept 14.",
    "subject": "history",
    "date": "2026-04-20"
  },
  {
    "number": 15,
    "question": "How is history concept 15 applied in practice?",
    "subject": "history",
    "date": "2026-04-20"
  },
  {
    "number": 16,
    "question": "What is the purpose of history concept 16?",
    "subject": "history",
    "date": "2026-04-20"
  },
  {
    "number": 17,
    "question": "Identify the key features of history concept 17.",
    "subject": "history",
    "date": "2026-04-20"
  },
  {
    "number": 18,
    "question": "What role does history concept 18 play?",
    "subject": "history",
    "date": "2026-04-20"
  },
  {
    "number": 19,
    "question": "Compare history concept 19 with similar concepts.",
    "subject": "history",
    "date": "2026-04-20"
  },
  {
    "number": 20,
    "question": "What challenges exist in understanding history concept 20?",
    "subject": "history",
    "date": "2026-04-20"
  },
  {
    "number": 21,
    "question": "What is the definition of history concept 21?",
    "subject": "history",
    "date": "2026-04-20"
  },
  {
    "number": 22,
    "question": "Which of the following best describes history concept 22?",
    "subject": "history",
    "date": "2026-04-20"
  },
  {
    "number": 23,
    "question": "Explain the concept of history concept 23.",
    "subject": "history",
    "date": "2026-04-20"
  },
  {
    "number": 24,
    "question": "What are the main characteristics of history concept 24?",
    "subject": "history",
    "date": "2026-04-20"
  },
  {
    "number": 25,
    "question": "How does history concept 25 relate to real-world applications?",
    "subject": "history",
    "date": "2026-04-20"
  },
  {
    "number": 26,
    "question": "What is the significance of history concept 26?",
    "subject": "history",
    "date": "2026-04-20"
  },
  {
    "number": 27,
    "question": "Name three key points about history concept 27.",
    "subject": "history",
    "date": "2026-04-20"
  },
  {
    "number": 28,
    "question": "Describe the process of history concept 28.",
    "subject": "history",
    "date": "2026-04-20"
  },
  {
    "number": 29,
    "question": "What is an example of history concept 29?",
    "subject": "history",
    "date": "2026-04-20"
  },
  {
    "number": 30,
    "question": "How would you categorize history concept 30?",
    "subject": "history",
    "date": "2026-04-20"
  },
  {
    "number": 31,
    "question": "Define history concept 31 in your own words.",
    "subject": "history",
    "date": "2026-04-20"
  },
  {
    "number": 32,
    "question": "What does history concept 32 mean?",
    "subject": "history",
    "date": "2026-04-20"
  },
  {
    "number": 33,
    "question": "Briefly explain history concept 33.",
    "subject": "history",
    "date": "2026-04-20"
  },
  {
    "number": 34,
    "question": "State one important fact about history concept 34.",
    "subject": "history",
    "date": "2026-04-20"
  },
  {
    "number": 35,
    "question": "How is history concept 35 applied in practice?",
    "subject": "history",
    "date": "2026-04-20"
  },
  {
    "number": 36,
    "question": "What is the purpose of history concept 36?",
    "subject": "history",
    "date": "2026-04-20"
  },
  {
    "number": 37,
    "question": "Identify the key features of history concept 37.",
    "subject": "history",
    "date": "2026-04-20"
  },
  {
    "number": 38,
    "question": "What role does history concept 38 play?",
    "subject": "history",
    "date": "2026-04-20"
  },
  {
    "number": 39,
    "question": "Compare history concept 39 with similar concepts.",
    "subject": "history",
    "date": "2026-04-20"
  },
  {
    "number": 40,
    "question": "What challenges exist in understanding history concept 40?",
    "subject": "history",
    "date": "2026-04-20"
  },
  {
    "number": 41,
    "question": "What is the definition of history concept 41?",
    "subject": "history",
    "date": "2026-04-20"
  },
  {
    "number": 42,
    "question": "Which of the following best describes history concept 42?",
    "subject": "history",
    "date": "2026-04-20"
  },
  {
    "number": 43,
    "question": "Explain the concept of history concept 43.",
    "subject": "history",
    "date": "2026-04-20"
  },
  {
    "number": 44,
    "question": "What are the main characteristics of history concept 44?",
    "subject": "history",
    "date": "2026-04-20"
  },
  {
    "number": 45,
    "question": "How does history concept 45 relate to real-world applications?",
    "subject": "history",
    "date": "2026-04-20"
  },
  {
    "number": 46,
    "question": "What is the significance of history concept 46?",
    "subject": "history",
    "date": "2026-04-20"
  },
  {
    "number": 47,
    "question": "Name three key points about history concept 47.",
    "subject": "history",
    "date": "2026-04-20"
  },
  {
    "number": 48,
    "question": "Describe the process of history concept 48.",
    "subject": "history",
    "date": "2026-04-20"
  },
  {
    "number": 49,
    "question": "What is an example of history concept 49?",
    "subject": "history",
    "date": "2026-04-20"
  },
  {
    "number": 50,
    "question": "How would you categorize history concept 50?",
    "subject": "history",
    "date": "2026-04-20"
  }
]